sanstem/InputLanguageError.py
sanstem/SanskritStemmer.py
sanstem/__init__.py
sanstem/Data/devanagari_languages.csv
sanstem/Data/noun_suffixes.csv
sanstem/Data/verb_suffixes.csv
sanstem-1.0.2.dist-info/LICENSE
sanstem-1.0.2.dist-info/METADATA
sanstem-1.0.2.dist-info/WHEEL
sanstem-1.0.2.dist-info/top_level.txt
sanstem-1.0.2.dist-info/RECORD
