Metadata-Version: 2.1
Name: sanstem
Version: 1.0.2
Summary: A rule-based stemmer for Sanskrit Verbs and Nouns
Home-page: https://github.com/sooraj-nair/sanstem
Author: Sooraj S Nair
Author-email: nairsooraj2000@gmail.com
License: MIT
Keywords: Sanskrit Stemmer
Platform: UNKNOWN
Classifier: Development Status :: 3 - Alpha
Classifier: Intended Audience :: Developers
Classifier: Topic :: Software Development :: Build Tools
Classifier: License :: OSI Approved :: MIT License
Classifier: Programming Language :: Python :: 3
Classifier: Programming Language :: Python :: 3.4
Classifier: Programming Language :: Python :: 3.5
Classifier: Programming Language :: Python :: 3.6
Requires-Dist: devatrans
Requires-Dist: morfessor
Requires-Dist: polyglot
Requires-Dist: pycld2
Requires-Dist: pyicu
